LICENSE
README.md
inferedge_moss_core-0.3.0.dist-info/METADATA
inferedge_moss_core-0.3.0.dist-info/WHEEL
inferedge_moss_core-0.3.0.dist-info/licenses/LICENSE
moss_core/__init__.py
moss_core/moss_core.cpython-314-aarch64-linux-gnu.so
inferedge_moss_core-0.3.0.dist-info/RECORD
