Metadata-Version: 2.4
Name: inferedge-moss-core
Version: 0.3.0
Classifier: Programming Language :: Python :: 3
Classifier: Programming Language :: Python :: 3.8
Classifier: Programming Language :: Python :: 3.9
Classifier: Programming Language :: Python :: 3.10
Classifier: Programming Language :: Python :: 3.11
Classifier: Programming Language :: Python :: 3.12
Classifier: Programming Language :: Python :: 3.13
Classifier: Programming Language :: Python :: 3.14
Classifier: Programming Language :: Rust
Classifier: License :: Other/Proprietary License
Classifier: Operating System :: OS Independent
License-File: LICENSE
Summary: Proprietary core index logic for Moss
Author: InferEdge, Inc.
License: SEE LICENSE IN LICENSE
Requires-Python: >=3.8
Project-URL: Homepage, https://github.com/InferEdge-Inc/moss
Project-URL: Issues, https://github.com/InferEdge-Inc/moss/issues
